wordgoal/VERSION
wordgoal/__init__.py
wordgoal/__main__.py
wordgoal/directory.py
wordgoal/document_types.py
wordgoal/invoke.py
wordgoal/py.typed
wordgoal/version.py
wordgoal/config/__init__.py
wordgoal/config/defaults.py
wordgoal/config/file.py
wordgoal/config/files.py
wordgoal/config/py.typed
wordgoal/config/style.py
wordgoal/documents/__init__.py
wordgoal/documents/markdown.py
wordgoal/documents/py.typed
wordgoal/documents/text.py
wordgoal/types/__init__.py
wordgoal/types/defaults.py
wordgoal/types/file.py
wordgoal/types/py.typed
wordgoal/types/style.py
wordgoal-1.1.0.dist-info/LICENSE
wordgoal-1.1.0.dist-info/METADATA
wordgoal-1.1.0.dist-info/WHEEL
wordgoal-1.1.0.dist-info/entry_points.txt
wordgoal-1.1.0.dist-info/top_level.txt
wordgoal-1.1.0.dist-info/RECORD
