Metadata-Version: 2.1
Name: wordgoal
Version: 1.1.0
Summary: Graphs your word count toward a goal
Home-page: https://github.com/cariad/wordgoal
Author: Cariad Eccleston
Author-email: cariad@hey.com
License: MIT License
Platform: UNKNOWN
Classifier: Development Status :: 5 - Production/Stable
Classifier: Environment :: Console
Classifier: Intended Audience :: Other Audience
Classifier: License :: OSI Approved :: MIT License
Classifier: Natural Language :: English
Classifier: Operating System :: OS Independent
Classifier: Programming Language :: Python :: 3 :: Only
Classifier: Programming Language :: Python :: 3.8
Classifier: Programming Language :: Python :: 3.9
Classifier: Topic :: Text Processing
Classifier: Topic :: Utilities
Classifier: Typing :: Typed
Requires-Python: >=3.8
Requires-Dist: boringmd (~=1.1.1)
Requires-Dist: colorama (~=0.4.4)
Requires-Dist: progrow (~=1.0)
Requires-Dist: pyyaml (~=5.4.1)
